modoboa_automua/__init__.py
modoboa_automua/apps.py
modoboa_automua/forms.py
modoboa_automua/handlers.py
modoboa_automua/models.py
modoboa_automua/modo_extension.py
modoboa_automua/frontend/__init__.py
modoboa_automua/frontend/formatters.py
modoboa_automua/frontend/settings.py
modoboa_automua/frontend/urls.py
modoboa_automua/frontend/views.py
modoboa_automua/migrations/0001_initial.py
modoboa_automua/migrations/0002_create_domain_mua_settings.py
modoboa_automua/migrations/__init__.py
modoboa_automua/static/automua/js/domains.js
modoboa_automua/templates/automua/domain_mua_widget.html
modoboa_automua/templates/automua/domain_settings_form.html
modoboa_automua-1.0.0.dist-info/LICENSE
modoboa_automua-1.0.0.dist-info/METADATA
modoboa_automua-1.0.0.dist-info/WHEEL
modoboa_automua-1.0.0.dist-info/top_level.txt
modoboa_automua-1.0.0.dist-info/RECORD
