Metadata-Version: 2.1
Name: modoboa-automua
Version: 1.0.0
Summary: Autoconfigure mail clients from Modoboa
Home-page: UNKNOWN
Author: Cliss XXI
Author-email: contact@cliss21.com
License: GNU AGPL-3
Project-URL: Bug Tracker, https://forge.cliss21.org/cliss21/modoboa-automua/issues
Project-URL: Source Code, https://forge.cliss21.org/cliss21/modoboa-automua
Keywords: modoboa,automx
Platform: UNKNOWN
Classifier: Development Status :: 4 - Beta
Classifier: Environment :: Web Environment
Classifier: Framework :: Django
Classifier: Intended Audience :: System Administrators
Classifier: License :: OSI Approved :: GNU Affero General Public License v3
Classifier: Operating System :: OS Independent
Classifier: Programming Language :: Python :: 3
Classifier: Programming Language :: Python :: 3.6
Classifier: Programming Language :: Python :: 3.7
Classifier: Programming Language :: Python :: 3.8
Classifier: Programming Language :: Python :: 3.9
Classifier: Programming Language :: Python :: 3 :: Only
Classifier: Topic :: Communications :: Email
Classifier: Topic :: Internet :: WWW/HTTP
Requires-Python: <4,>=3.7
Requires-Dist: defusedxml
Requires-Dist: modoboa (<2.0,>=1.17)
Provides-Extra: test
Requires-Dist: black ; extra == 'test'
Requires-Dist: coverage ; extra == 'test'
Requires-Dist: flake8-black ; extra == 'test'
Requires-Dist: flake8-isort ; extra == 'test'
Requires-Dist: flake8 (>=3.5) ; extra == 'test'
Requires-Dist: isort (>=5.0) ; extra == 'test'
